setup.py
DistProPy/Binomialdistribution.py
DistProPy/Gaussiandistribution.py
DistProPy/Generaldistribution.py
DistProPy/__init__.py
DistProPy.egg-info/PKG-INFO
DistProPy.egg-info/SOURCES.txt
DistProPy.egg-info/dependency_links.txt
DistProPy.egg-info/not-zip-safe
DistProPy.egg-info/top_level.txt