Metadata-Version: 2.1
Name: DistProPy
Version: 0.1
Summary: Gaussian and Binomial distributions
Author: Carlos Bonilla
Author-email: cabonillao.oc@gmail.com
